{
	"ment": [
		{
			"seq": 4,
			"title": "백엔드개발자 / AA",
			"recruit": {
				"text": {
					"recruit1": ["학력 : 전문대학 이상을 졸업한 자로 컴퓨터 정보통신 분야 전공자", "경력 : 신입, 경력(2년 이상)"],
					"recruit2": ["컴퓨터/시스템공학", "정보처리기사, 정보통신산업기사"],
					"recruit3": [
						"근무형태 : 정규직, 계약직",
						"근무일시 : 주 5일(월~금) 오전 9시~오후 6시",
						"근무지역 : 서울특별시 강남구 강남대로 94길 67, 3층(역삼동, 도연빌딩)"
					]
				},
				"img": "/recruit-process2.png",
				"startDate": "2022-12-20",
				"endDate": "2024-02-15"
			},
			"date": "2022-12-20",
			"note": ""
		},
		{
			"seq": 3,
			"title": "SI개발",
			"recruit": {
				"text": {
					"recruit1": ["학력 : 전문대학 이상을 졸업한 자로 컴퓨터 정보통신 분야 전공자", "경력 : 경력(2년 이상)"],
					"recruit2": ["컴퓨터/시스템공학", "정보처리기사, 정보통신산업기사"],
					"recruit3": [
						"근무형태 : 정규직, 계약직",
						"근무일시 : 주 5일(월~금) 오전 9시~오후 6시",
						"근무지역 : 서울특별시 강남구 강남대로 94길 67, 3층(역삼동, 도연빌딩)"
					]
				},
				"img": "/recruit-process2.png",
				"startDate": "2022-12-20",
				"endDate": "2024-02-15"
			},
			"date": "2022-12-20",
			"note": ""
		},
		{
			"seq": 2,
			"title": "컨설팅 중/고급",
			"recruit": {
				"text": {
					"recruit1": ["학력 : 전문대학 이상을 졸업한 자로 컴퓨터 정보통신 분야 전공자", "경력 : 신입, 경력(2년 이상)"],
					"recruit2": ["컴퓨터/시스템공학", "정보처리기사, 정보통신산업기사"],
					"recruit3": [
						"근무형태 : 정규직, 계약직",
						"근무일시 : 주 5일(월~금) 오전 9시~오후 6시",
						"근무지역 : 서울특별시 강남구 강남대로 94길 67, 3층(역삼동, 도연빌딩)"
					]
				},
				"img": "/recruit-process2.png",
				"startDate": "2022-12-20",
				"endDate": "2023-02-15"
			},
			"date": "2022-12-20",
			"note": ""
		},
		{
			"seq": 1,
			"title": "프로젝트 PM/PL",
			"recruit": {
				"text": {
					"recruit1": ["학력 : 전문대학 이상을 졸업한 자로 컴퓨터 정보통신 분야 전공자", "경력 : 경력 3년 이상"],
					"recruit2": ["컴퓨터/시스템공학", "정보처리기사, 정보통신산업기사"],
					"recruit3": [
						"근무형태 : 정규직, 계약직",
						"근무일시 : 주 5일(월~금) 오전 9시~오후 6시",
						"근무지역 : 서울특별시 강남구 강남대로 94길 67, 3층(역삼동, 도연빌딩)"
					]
				},
				"img": "/recruit-process2.png",
				"startDate": "2021-12-20",
				"endDate": "2022-01-13"
			},
			"date": "2022-12-20",
			"note": ""
		}
	]
}
